binary_to_gray/b2g.v
module b2g (
    input [3:0]x, output [3:0]y
);
    assign y[3] = x[3];
    assign y[2] = x[3]^x[2];
    assign y[1] = x[2]^x[1];
    assign y[0] = x[1]^x[0];
endmodule

binary_to_gray/tb_b2g.v
`timescale 1ps/1ps
module tb_b2g;
    reg [3:0]x;
    wire [3:0]y;
    b2g DUT(.x(x), .y(y));

    integer i;
    initial begin
        $dumpfile("output.vcd");
        $dumpvars(0,tb_b2g);
        for(i=0; i<16 ;i=i+1)
        begin
            x = i;
            #10;
        end
        $finish();
    end
    initial $monitor("x = %b, y = %b",x,y);
endmodule

binary_to_gray/output.vcd
$date
	Wed Dec 21 08:31:19 2022
$end
$version
	Icarus Verilog
$end
$timescale
	1ps
$end
$scope module tb_b2g $end
$var wire 4 ! y [3:0] $end
$var reg 4 " x [3:0] $end
$var integer 32 # i [31:0] $end
$scope module DUT $end
$var wire 4 $ x [3:0] $end
$var wire 4 % y [3:0] $end
$upscope $end
$upscope $end
$enddefinitions $end
#0
$dumpvars
b0 %
b0 $
b0 #
b0 "
b0 !
$end
#10
b1 !
b1 %
b1 "
b1 $
b1 #
#20
b11 !
b11 %
b10 "
b10 $
b10 #
#30
b10 !
b10 %
b11 "
b11 $
b11 #
#40
b110 !
b110 %
b100 "
b100 $
b100 #
#50
b111 !
b111 %
b101 "
b101 $
b101 #
#60
b101 !
b101 %
b110 "
b110 $
b110 #
#70
b100 !
b100 %
b111 "
b111 $
b111 #
#80
b1100 !
b1100 %
b1000 "
b1000 $
b1000 #
#90
b1101 !
b1101 %
b1001 "
b1001 $
b1001 #
#100
b1111 !
b1111 %
b1010 "
b1010 $
b1010 #
#110
b1110 !
b1110 %
b1011 "
b1011 $
b1011 #
#120
b1010 !
b1010 %
b1100 "
b1100 $
b1100 #
#130
b1011 !
b1011 %
b1101 "
b1101 $
b1101 #
#140
b1001 !
b1001 %
b1110 "
b1110 $
b1110 #
#150
b1000 !
b1000 %
b1111 "
b1111 $
b1111 #
#160
b10000 #
