gray_to_binary/g2b.v
module g2b (
    input [3:0]y, output [3:0]x
);
    assign x[3] = y[3];
    assign x[2] = x[3]^y[2];
    assign x[1] = x[2]^y[1];
    assign x[0] = x[1]^y[0];
endmodule

gray_to_binary/tb_g2b.v
`timescale 1ps/1ps
module tb_g2b;
    reg [3:0]y;
    wire [3:0]x;
    g2b DUT(.x(x), .y(y));

    integer i;
    initial begin
        $dumpfile("output.vcd");
        $dumpvars(0,tb_g2b);
        for(i=0; i<16 ;i=i+1)
        begin
            y = i;
            #10;
        end
        $finish();
    end
    initial $monitor("y = %b, x = %b",y,x);
endmodule

gray_to_binary/output.vcd
$date
	Wed Dec 21 08:34:49 2022
$end
$version
	Icarus Verilog
$end
$timescale
	1ps
$end
$scope module tb_g2b $end
$var wire 4 ! x [3:0] $end
$var reg 4 " y [3:0] $end
$var integer 32 # i [31:0] $end
$scope module DUT $end
$var wire 4 $ y [3:0] $end
$var wire 4 % x [3:0] $end
$upscope $end
$upscope $end
$enddefinitions $end
#0
$dumpvars
b0 %
b0 $
b0 #
b0 "
b0 !
$end
#10
b1 !
b1 %
b1 "
b1 $
b1 #
#20
b11 !
b11 %
b10 "
b10 $
b10 #
#30
b10 !
b10 %
b11 "
b11 $
b11 #
#40
b111 !
b111 %
b100 "
b100 $
b100 #
#50
b110 !
b110 %
b101 "
b101 $
b101 #
#60
b100 !
b100 %
b110 "
b110 $
b110 #
#70
b101 !
b101 %
b111 "
b111 $
b111 #
#80
b1111 !
b1111 %
b1000 "
b1000 $
b1000 #
#90
b1110 !
b1110 %
b1001 "
b1001 $
b1001 #
#100
b1100 !
b1100 %
b1010 "
b1010 $
b1010 #
#110
b1101 !
b1101 %
b1011 "
b1011 $
b1011 #
#120
b1000 !
b1000 %
b1100 "
b1100 $
b1100 #
#130
b1001 !
b1001 %
b1101 "
b1101 $
b1101 #
#140
b1011 !
b1011 %
b1110 "
b1110 $
b1110 #
#150
b1010 !
b1010 %
b1111 "
b1111 $
b1111 #
#160
b10000 #
