binary_to_gray/b2g.v
module b2g (
    input [3:0]x, output [3:0]y
);
    assign y[3] = x[3];
    assign y[2] = x[3]^x[2];
    assign y[1] = x[2]^x[1];
    assign y[0] = x[1]^x[0];
endmodule

gray_counter/gray_counter.v
`include "b2g.v"
module gray_counter (
    input clk,rst_n, output [3:0]q
);
reg [3:0]b;
always @(posedge clk)
begin
   if(~rst_n)
   b<=4'b0000;
   else
   b<=b+4'b0001;
end
b2g U1(.x(b), .y(q));
    
endmodule

gray_counter/tb_gray_counter.v
`timescale 1ps/1ps
module tb_gray_counter;
    reg clk,rst_n;
    wire [3:0]q;

    gray_counter DUT(.clk(clk), .rst_n(rst_n), .q(q));
    initial begin
        clk = 1'b0;
        forever #5 clk = !clk;
    end

    initial $monitor("B = %b, Q = %b",DUT.b,q);
    initial begin
        $dumpfile("output.vcd");
        $dumpvars(0,tb_gray_counter);
        rst_n = 0;
        #10;
        rst_n = 1;
        #200;
        $finish;
    end
endmodule

gray_counter/output.vcd
$date
	Sat Dec 24 08:05:10 2022
$end
$version
	Icarus Verilog
$end
$timescale
	1ps
$end
$scope module tb_gray_counter $end
$var wire 4 ! q [3:0] $end
$var reg 1 " clk $end
$var reg 1 # rst_n $end
$scope module DUT $end
$var wire 1 " clk $end
$var wire 1 # rst_n $end
$var wire 4 $ q [3:0] $end
$var reg 4 % b [3:0] $end
$scope module U1 $end
$var wire 4 & x [3:0] $end
$var wire 4 ' y [3:0] $end
$upscope $end
$upscope $end
$upscope $end
$enddefinitions $end
#0
$dumpvars
bx '
bx &
bx %
bx $
0#
0"
bx !
$end
#5
b0 !
b0 $
b0 '
b0 %
b0 &
1"
#10
0"
1#
#15
b1 !
b1 $
b1 '
b1 %
b1 &
1"
#20
0"
#25
b11 !
b11 $
b11 '
b10 %
b10 &
1"
#30
0"
#35
b10 !
b10 $
b10 '
b11 %
b11 &
1"
#40
0"
#45
b110 !
b110 $
b110 '
b100 %
b100 &
1"
#50
0"
#55
b111 !
b111 $
b111 '
b101 %
b101 &
1"
#60
0"
#65
b101 !
b101 $
b101 '
b110 %
b110 &
1"
#70
0"
#75
b100 !
b100 $
b100 '
b111 %
b111 &
1"
#80
0"
#85
b1100 !
b1100 $
b1100 '
b1000 %
b1000 &
1"
#90
0"
#95
b1101 !
b1101 $
b1101 '
b1001 %
b1001 &
1"
#100
0"
#105
b1111 !
b1111 $
b1111 '
b1010 %
b1010 &
1"
#110
0"
#115
b1110 !
b1110 $
b1110 '
b1011 %
b1011 &
1"
#120
0"
#125
b1010 !
b1010 $
b1010 '
b1100 %
b1100 &
1"
#130
0"
#135
b1011 !
b1011 $
b1011 '
b1101 %
b1101 &
1"
#140
0"
#145
b1001 !
b1001 $
b1001 '
b1110 %
b1110 &
1"
#150
0"
#155
b1000 !
b1000 $
b1000 '
b1111 %
b1111 &
1"
#160
0"
#165
b0 !
b0 $
b0 '
b0 %
b0 &
1"
#170
0"
#175
b1 !
b1 $
b1 '
b1 %
b1 &
1"
#180
0"
#185
b11 !
b11 $
b11 '
b10 %
b10 &
1"
#190
0"
#195
b10 !
b10 $
b10 '
b11 %
b11 &
1"
#200
0"
#205
b110 !
b110 $
b110 '
b100 %
b100 &
1"
